djgentelella/__init__.py
djgentelella/admin.py
djgentelella/apps.py
djgentelella/chartjs.py
djgentelella/elements.py
djgentelella/exceptions.py
djgentelella/groute.py
djgentelella/gtselects.py
djgentelella/models.py
djgentelella/models_manager.py
djgentelella/objectmanagement.py
djgentelella/settings.py
djgentelella/urls.py
djgentelella/utils.py
djgentelella/blog/__init__.py
djgentelella/blog/admin.py
djgentelella/blog/apps.py
djgentelella/blog/forms.py
djgentelella/blog/models.py
djgentelella/blog/sitemaps.py
djgentelella/blog/tests.py
djgentelella/blog/urls.py
djgentelella/blog/views.py
djgentelella/blog/migrations/0001_initial.py
djgentelella/blog/migrations/__init__.py
djgentelella/blog/static/images/article.png
djgentelella/blog/templates/gentelella/blog/category_add.html
djgentelella/blog/templates/gentelella/blog/entry_delete.html
djgentelella/blog/templates/gentelella/blog/entry_detail.html
djgentelella/blog/templates/gentelella/blog/entry_form.html
djgentelella/blog/templates/gentelella/blog/entry_list.html
djgentelella/blog/templatetags/__init__.py
djgentelella/blog/templatetags/blog_tags.py
djgentelella/blog/tests/__init__.py
djgentelella/blog/tests/test_entry_detail.py
djgentelella/blog/tests/test_entry_forms.py
djgentelella/blog/tests/test_entry_listing.py
djgentelella/blog/tests/test_models.py
djgentelella/blog/tests/test_sitemaps.py
djgentelella/blog/tests/test_templatetags.py
djgentelella/chunked_upload/__init__.py
djgentelella/chunked_upload/constants.py
djgentelella/chunked_upload/models.py
djgentelella/chunked_upload/response.py
djgentelella/chunked_upload/views.py
djgentelella/cruds/__init__.py
djgentelella/cruds/base.py
djgentelella/cruds/filter.py
djgentelella/cruds/inline_crud.py
djgentelella/cruds/utils.py
djgentelella/decorators/__init__.py
djgentelella/decorators/perms.py
djgentelella/fields/__init__.py
djgentelella/fields/catalog.py
djgentelella/fields/drfdatetime.py
djgentelella/fields/files.py
djgentelella/fields/tree.py
djgentelella-0.5.5.dist-info/AUTHORS
djgentelella-0.5.5.dist-info/LICENSE.txt
djgentelella-0.5.5.dist-info/METADATA
djgentelella-0.5.5.dist-info/WHEEL
djgentelella-0.5.5.dist-info/top_level.txt
djgentelella-0.5.5.dist-info/RECORD
