Metadata-Version: 2.1
Name: djgentelella
Version: 0.5.5
Summary: Help building extra widgets for forms and speciall methods to render forms in templates
Author-email: Solvosoft <info@solvosoft.com>
Maintainer-email: Luis Zarate Montero <luis.zarate@solvosoft.com>
License: GNU GENERAL PUBLIC LICENSE
Project-URL: Homepage, https://github.com/Solvosoft/django-gentelella-widgets
Project-URL: Bug Reports, https://github.com/Solvosoft/django-gentelella-widgets/issues
Project-URL: Funding, https://github.com/sponsors/Solvosoft
Keywords: Django,selects,development,forms,framework,widgets
Classifier: Development Status :: 4 - Beta
Classifier: Intended Audience :: Developers
Classifier: Topic :: Software Development :: Build Tools
Classifier: Environment :: Web Environment
Classifier: Framework :: Django
Classifier: Framework :: Django :: 5
Classifier: Operating System :: OS Independent
Classifier: Topic :: Internet :: WWW/HTTP :: Dynamic Content
Classifier: Topic :: Internet :: WWW/HTTP :: WSGI :: Application
Classifier: Topic :: Software Development :: Libraries
Classifier: Topic :: Software Development :: Libraries :: Python Modules
Classifier: Topic :: Software Development :: Version Control :: Git
Classifier: Programming Language :: Python :: 3
Classifier: Programming Language :: Python :: 3.11
Classifier: Programming Language :: Python :: 3.12
Classifier: Programming Language :: Python :: 3 :: Only
Requires-Python: >=3.11
License-File: LICENSE.txt
License-File: AUTHORS
Requires-Dist: django-tree-queries>=0.11.0
Requires-Dist: djangoajax>=3.3
Requires-Dist: django-markitup>=4.0.0
Requires-Dist: markdown
Requires-Dist: Pillow
Requires-Dist: djangorestframework>=3.13
Requires-Dist: django>=4.2
Requires-Dist: django-filter>=22.1
Provides-Extra: dev
Requires-Dist: pylp; extra == "dev"
Requires-Dist: pylpconcat; extra == "dev"
Requires-Dist: css-html-js-minify; extra == "dev"
Provides-Extra: firmador
Requires-Dist: django-cors-headers==4.6.0; extra == "firmador"
Requires-Dist: uvicorn==0.32.1; extra == "firmador"
Requires-Dist: uvicorn-worker==0.2.0; extra == "firmador"
Requires-Dist: channels==4.2.0; extra == "firmador"
Requires-Dist: wsproto==1.2.0; extra == "firmador"
Requires-Dist: requests==2.32.4; extra == "firmador"
Provides-Extra: test
